panduza_plg_devfs_gpio/__init__.py
panduza_plg_devfs_gpio/sysgpio.py
panduza_plg_devfs_gpio-0.0.1.dist-info/METADATA
panduza_plg_devfs_gpio-0.0.1.dist-info/WHEEL
panduza_plg_devfs_gpio-0.0.1.dist-info/top_level.txt
panduza_plg_devfs_gpio-0.0.1.dist-info/RECORD
